FreecadParametricFEA/__init__.py
FreecadParametricFEA/freecadmodel.py
FreecadParametricFEA/loghandler.py
FreecadParametricFEA/parametric.py
FreecadParametricFEA/register_freecad.py
freecadparametricfea-0.3.dist-info/LICENSE.md
freecadparametricfea-0.3.dist-info/METADATA
freecadparametricfea-0.3.dist-info/WHEEL
freecadparametricfea-0.3.dist-info/RECORD
