Metadata-Version: 2.1
Name: freecadparametricfea
Version: 0.3
Summary: A flexible parametric FEA library based on FreeCAD
Home-page: https://github.com/da-crivelli/freecad-parametric-fea
License: LGPL-2.1-or-later
Author: Davide Crivelli,
Author-email: da.crivelli@gmail.com
Requires-Python: >=3.8.10,<3.9.0
Classifier: Development Status :: 2 - Pre-Alpha
Classifier: License :: OSI Approved
Classifier: License :: OSI Approved :: GNU Lesser General Public License v2 or later (LGPLv2+)
Classifier: Operating System :: OS Independent
Classifier: Programming Language :: Python :: 3
Classifier: Programming Language :: Python :: 3.8
Requires-Dist: numpy (>=1.24.1,<2.0.0)
Requires-Dist: pandas (>=1.5.2,<2.0.0)
Requires-Dist: plotly (>=5.12.0,<6.0.0)
Requires-Dist: pyside2 (>=5.15.2.1,<6.0.0.0)
Requires-Dist: tqdm (>=4.64.1,<5.0.0)
Project-URL: Repository, https://github.com/da-crivelli/freecad-parametric-fea
